MAP/HelloWorld.py
PYActivate/PYActivate.py
PYActivate-0.0.1.dist-info/METADATA
PYActivate-0.0.1.dist-info/WHEEL
PYActivate-0.0.1.dist-info/top_level.txt
PYActivate-0.0.1.dist-info/RECORD
